parsegrammar/__init__.py
parsegrammar/grammar.py
parsegrammar-0.1.0.dist-info/LICENSE
parsegrammar-0.1.0.dist-info/METADATA
parsegrammar-0.1.0.dist-info/WHEEL
parsegrammar-0.1.0.dist-info/top_level.txt
parsegrammar-0.1.0.dist-info/RECORD
