Metadata-Version: 2.1
Name: parsegrammar
Version: 0.1.0
Summary: A library with Symbol Graph and Grammar classes
Home-page: https://github.com/lorkaan/parsegrammar.git
Author: Laurkan Rodriguez
Author-email: laurkan@engineer.com
License: UNKNOWN
Download-URL: https://github.com/lorkaan/parsegrammar/archive/v0.1.0.tar.gz
Platform: UNKNOWN
Classifier: Intended Audience :: Developers
Classifier: Programming Language :: Python :: 3.8
Classifier: Operating System :: OS Independent
